server/search_suse_documentation.py
suse_documentation_mcp_server-0.44.0.dist-info/METADATA
suse_documentation_mcp_server-0.44.0.dist-info/WHEEL
suse_documentation_mcp_server-0.44.0.dist-info/entry_points.txt
suse_documentation_mcp_server-0.44.0.dist-info/top_level.txt
suse_documentation_mcp_server-0.44.0.dist-info/RECORD
