Metadata-Version: 2.4
Name: suse-documentation-mcp-server
Version: 0.44.0
Summary: MCP server implementation for web search using Open WebUI Web search
Requires-Python: >=3.12
Requires-Dist: python-dotenv>=1.0.1
Requires-Dist: mcp[cli]>=1.4.1
Requires-Dist: httpx>=0.28.1
Requires-Dist: markitdown>=0.1.2
